crumble/__init__.py
crumble/crumble.py
crumble/fastmatch.py
crumble/data/iso_country.csv
crumble/data/public_suffix_list.dat
crumble/data/tld-country.tsv
crumble/data/tlds-alpha-by-domain.txt
crumble-0.5.dist-info/LICENSE
crumble-0.5.dist-info/METADATA
crumble-0.5.dist-info/WHEEL
crumble-0.5.dist-info/top_level.txt
crumble-0.5.dist-info/RECORD
