Metadata-Version: 2.1
Name: crumble
Version: 0.5
Summary: Cognism URL component parser. General purpose.
Home-page: https://www.github.com/cognism/crumble.git
Author: James Hodson
Author-email: james.hodson@cognism.com
License: lGPLv3
Keywords: cognism,machine learning,URL parsing
Platform: UNKNOWN
Classifier: Development Status :: 4 - Beta
Classifier: Programming Language :: Python :: 3
Classifier: Operating System :: OS Independent
License-File: LICENSE
